Workbook

Sheet READ ME
A1: Workbook Documentation — README
A2: Read this tab before editing any other sheet in this workbook.
A4: 1 · Overview
A5: This workbook is the central reference for managing organisational compliance, assessment activities, data classification and more. It consolidates three operational domains into a single, auditable record; this will be a living document as more info gets added to this document, the corresponding tabs along readme ta will also be updated • Certification – tracks staff, system, and vendor certifications, expiry dates, and renewal ownership. • Assessment – records risk and control assessments, findings, severity ratings, remediation owners, and resolution status. • Data Classification – inventories data assets, assigns sensitivity levels, and documents handling requirements and data ownership. Update each tab as changes occur. Do not alter column headers or delete rows — mark outdated records as 'Retired' or 'Closed' instead.
A7: 2 · Tab Descriptions
A8: Tab Name | B8: Description & Purpose
A9: README | B9: This sheet provides the workbook overview, field definitions, usage instructions, Always read before editing other tabs.
A10: Certification | B10: Tracks all active and applicable certifications. Each row = one certification record.
A11: list of FMAs | B11: Records risk, compliance, and audit assessments with primary and secondary Each row = one assessment item.
A12: Data Classification | B12: Data classification for both Information and AI systems. Each row represents one classification level (1 = Public through 5 = Restricted) and documents the level name, what qualifies for it, the impact of unauthorised disclosure, the associated risk rating, and representative example data.
A13: PSP Framework | B13: PSP stands for policies standards and procedures This sheet gives an overview framework for PSP
A14: Security Program | B14: This sheet provides an overview of building a Security GRC program from scratch. The framework is designed to be user-friendly and can be dynamically edited as the program evolves. It also includes links to frameworks for policies, standards, and procedures for organizations looking to establish their program from the ground up.
A15: Topics to discuss with Lisa | B15: topics to be discussed with Lisa during weekly calls

Sheet list of FMAs
B1: Cybersecurity Framework/Certification Selection and Maturity Tool | M1: Legend - Startup / Small <100 people Mid-Size 100 - 2000 people Large Enterprise 2000+ | S1: DO NOT REFERENCE THIS COLUMN
A2: Framework/ Assessment | B2: Geography | C2: Type | D2: Rating | E2: Best for (who should pursue) | F2: Purpose | G2: Applicable Organization Size | H2: Business Value | I2: Quantified impact | J2: Assessment Mode (who manages) | K2: Levels | L2: Output Type | M2: Output Mode | N2: Typical Duration | O2: Estimated Cost | P2: Alternative | Q2: Mandatory? | R2: Additional Info | S2: Additional details to consider /add to this sheet | T2: Who Should Prioritise First
A3: NIST CSF 2.0 | B3: US / intl | C3: Framework | D3: 0 | E3: All industries | F3: Enterprise risk & security posture framework for general purpose framework use | G3: Startup / Mid-size / Enterprise | H3: Business-aligned cybersecurity | I3: ↓ compliance effort 30–50% | J3: Self / Third-party | K3: Maturity tiers: Tier 1 (Partial) → Tier 2 (Risk Informed) → Tier 3 (Repeatable) → Tier 4 (Adaptive) [Not a pass/fail — tiers describe risk management practice maturity] | L3: Maturity score + roadmap | M3: Internal report / PDF | N3: 2-6 months | O3: $50K–$200K | P3: ISO 27001, CIS18 | Q3: Voluntary - Start here | R3: - covers 6 core functions - risk based prioritization emphasis - lower cost and customizable | S3: - Who should pursue | T3: Any organisation beginning a security programme or preparing for regulatory alignment. Ideal first framework for teams that need a common risk language before committing to a certification.
A4: HITRUST CSF | B4: US / intl | C4: Certification | D4: 0 | E4: Healthcare / fintech | F4: Certifiable framework primarly used in health care aligning with HIPAA and ISO | G4: Mid-size / Enterprise | H4: Unified cert reduces audit duplication | I4: ↓ audit effort 30–50% | J4: Third-party audit | K4: Certification levels: e1 (Essentials 1 — implemented) → i1 (Implemented 1 — self-assessed) → r2 (Risk-based 2 — validated by assessor) [Each level is independently certifiable] | L4: Certification | M4: PDF certificate + report | N4: 6-12 months | O4: $150k-$500k | P4: ISO 27001, SOC 2 | Q4: Voluntary | R4: - includes ~1,800 controls over 19 domains - time consuming, heavy costs and prescriptive | S4: - who manages / audits | T4: Healthcare-adjacent SaaS vendors, digital health platforms, and any business handling PHI that needs a single certification recognised by hospital systems, payers, and health-tech partners.
A5: NIST RMF | B5: US / intl | C5: Framework | D5: 0 | E5: Federal gov contractors | F5: Manage cybersecurity risks through a systematic, repeatable process. | G5: Enterprise | H5: Structured risk lifecycle | I5: ↓ control gaps 20–40% | J5: Self / Third-party | K5: Process stages: Categorise → Select → Implement → Assess → Authorise → Monitor [Stages lead to an ATO decision — not a maturity rating] | L5: ATO decision | M5: Formal gov package (PDF) | N5: 6–18 months | O5: $200K–$800K | P5: ISO 27001, 800-53 | Q5: Mandatory (conditional) | R5: - Step-based process: Categorise → Select → Implement → Assess → Authorise → Monitor - Aligned with FISMA requirements for all US federal agencies - Produces a formal ATO (Authority to Operate) — the legal basis for operating a federal system - Common controls baseline drawn from NIST SP 800-53 | S5: - Business Value (why businesses /orgs should pursue a cert) - rationale | T5: Software and cloud vendors seeking or holding US federal contracts. Essential for any organisation within the DoD, civilian agency, or intelligence community supply chain.
A6: NIST AI RMF | B6: US / intl | C6: Framework | D6: 0 | E6: AL/ML adopters | F6: AI governance and risk management | G6: Startup / Mid-size / Enterprise | H6: Trustworthy AI adoption | I6: ↓ AI risk exposure 20–30% | J6: Self | K6: Functional domains: Govern → Map → Measure → Manage [Profile-based — no numeric maturity score; progress measured via Current vs Target Profile gap] | L6: Profile + roadmap | M6: PDF report | N6: 3-9 months | O6: $75k-$250k | P6: ISO 42001, EU AI Act | Q6: Voluntary | R6: Govern–Map–Measure–Manage, bias, explainability, model risk | S6: - historical context of the framework/process/assessment | T6: Any organisation building, deploying, or procuring AI systems — particularly those selling into regulated industries or EU markets. A priority for AI product teams ahead of EU AI Act enforcement.
A7: NIST Privacy Framework | B7: US / intl | C7: Framework | D7: 0 | E7: All industries - Data driven orgs | F7: Privacy risk management | G7: Startup / Mid-size / Enterprise | H7: Privacy risk management | I7: ↓ privacy incidents 20–40% | J7: Self | K7: Maturity tiers: Tier 1 (Partial) → Tier 2 (Risk Informed) → Tier 3 (Repeatable) → Tier 4 (Adaptive) [Same tier structure as NIST CSF; privacy-specific profile added] | L7: Profile + gap analysis | M7: PDF report | N7: 2-6 months | O7: $50k-$200k | P7: ISO 27701, GDPR | Q7: Voluntary | R7: - Voluntary framework — not a regulation - Pairs well with NIST CSF 2.0 and ISO 27701 - Covers 5 core functions: Identify-P, Govern-P, Control-P, Communicate-P, Protect-P - Maps to GDPR, CCPA, and APEC Privacy Framework | S7: - quick useful links/documentation (such as official guids , controls etc) - auditor's perspective of helpfulness (GRC perspective) | T7: Organisations subject to GDPR, CCPA, or handling consumer data at scale. Especially valuable for US companies needing a structured privacy risk programme without a mandatory regulatory driver.
A8: NIST SSDF-EO 14028 | B8: US / intl | C8: Framework | D8: 0 | E8: All Industries - Product/Eng orgs | F8: Secure SDLC (SSDLC) practices | G8: Startup / Mid-size / Enterprise | H8: Secure SDLC | I8: ↓ vulnerabilities in prod 30–50% | J8: Self / Audit | K8: Task-level compliance: practices grouped into 4 groups (PO, RV, DT, RS) with task completion tracked [No numeric maturity tiers — compliance measured against task completion status] | L8: Attestation / SBOM | M8: Attestation + SBOM docs | N8: 3-6 months | O8: $50K–$200K | P8: OWASP SAMM | Q8: Mandatory (conditional) | R8: Secure coding, SBOM, DevSecOps | S8: - Historical context: SSDF published 2020; EO 14028 (May 2021) made it mandatory for federal software vendors - Auditor's perspective: SBOM quality and completeness are the primary assessment focus - Links: csrc.nist.gov/Projects/ssdf | T8: Software vendors supplying to US federal agencies or large enterprises that require SBOM documentation. Critical for any vendor whose software runs in government or critical infrastructure environments.
A9: Cyber Maturity Model Certification | B9: International | C9: Assessment | D9: 0 | E9: DoD contractors | F9: Measure org-wide cyber maturity | G9: Mid-size / Enterprise | H9: DoD market access | I9: Enables $M–$B defense contracts | J9: Third-party audit | K9: Maturity levels: Level 1 (Basic cyber hygiene) → Level 2 (Advanced — NIST 800-171) → Level 3 (Expert — NIST 800-172) [Each level is gate-controlled; Level 2+ requires C3PAO third-party assessment] | L9: Certification | M9: PDF certificate | N9: 2-4 months | O9: $25k-$100k | P9: NIST 800-171 | Q9: Mandatory (conditional) | R9: - Level 1: 17 practices (FAR 52.204-21) — self-attestation - Level 2: 110 practices from NIST SP 800-171 — C3PAO required - Level 3: 24 additional practices from NIST SP 800-172 — government-led assessment - Mandatory for all DoD prime and subcontractors handling CUI | S9: - Historical context: CMMC 1.0 launched 2020; CMMC 2.0 (2021) streamlined from 5 levels to 3 - Auditor's perspective: Gap assessment against NIST SP 800-171 is essential before engaging a C3PAO - Links: dodcmmc.mil | T9: US defence contractors and subcontractors at any tier of the DoD supply chain. Required for contract award — organisations should confirm their CMMC level requirement before beginning.
A10: NIS2 Directive | B10: EU | C10: Regulation | D10: 0 | E10: EU critical infra | F10: Critical infrastructure cybersecurity | G10: Mid-size / Enterprise | H10: EU compliance | I10: Avoid fines up to 2% revenue | J10: Regulatory audit | K10: Compliance status: Compliant / Partially Compliant / Non-Compliant [Regulation — no maturity tiers; compliance measured against 10 minimum security measures] | L10: Compliance status | M10: Regulatory report / submission | N10: 6–12 months | O10: $100K–$400K | P10: ISO 27001 | Q10: Mandatory | R10: Risk mgmt, incident reporting, governance | S10: - Historical context: NIS2 replaced NIS1 Directive (2016); member states had until October 2024 to transpose - Auditor's perspective: Supply chain security (Article 21) is the area organisations most commonly underestimate - Links: eur-lex.europa.eu/NIS2 | T10: EU-based operators of essential services (energy, transport, health, water, digital infrastructure) and important entities. Also relevant for non-EU companies with significant EU operations.
A11: EU AI Act | B11: EU | C11: Regulation | D11: 0 | E11: AI companies in EU | F11: AI regulatory compliance | G11: Mid-size / Enterprise | H11: AI compliance | I11: Avoid fines up to 6% revenue | J11: Regulatory audit | K11: Risk-based tiers: Prohibited / High-risk / Limited-risk / Minimal-risk [Tier determined by AI system use case, not org maturity; High-risk systems require conformity assessment] | L11: Compliance declaration | M11: PDF + CE documentation | N11: 6-18 months | O11: $150k-$500k | P11: ISO 42001 | Q11: Mandatory | R11: World’s first legally binding AI framework, regulating systems by risk to ensure safety, transparency, ethics, and protection of fundamental rights. | S11: NIST SP | T11: Organisations developing or deploying AI systems in the EU, or selling AI-enabled products to EU customers. Priority for any company with high-risk AI use cases (HR, credit, healthcare, law enforcement).
A12: DORA | B12: EU | C12: Regulation | E12: EU financial services | F12: A safer, more consistent, and resilient digital environment for the EU financial system | G12: Mid-size / Enterprise | H12: Operational resilience | I12: ↓ downtime losses 20–40% | J12: Regulatory audit | K12: Compliance status: Compliant / Non-Compliant [Regulation — no maturity tiers; assessed across 5 ICT risk pillars: Governance, Protection, Detection, Response, Recovery] | L12: Compliance report | M12: Regulatory submission | N12: 6-12+ months | O12: €25M - €150M $25M - $170M | P12: ISO 22301 | Q12: Mandatory | R12: to ensure financial entities can withstand, respond to, and recover from ICT (Information and Communication Technology) disruptions and cyberattacks. | S12: - Historical context: DORA finalised November 2022; application date January 17, 2025 - Auditor's perspective: ICT third-party register and contractual requirements (Article 30) are the most operationally complex aspect - Links: eur-lex.europa.eu/DORA | T12: EU-regulated financial entities: banks, investment firms, insurers, payment institutions, crypto-asset service providers. Also relevant for their critical ICT third-party providers.
A13: Cryptocurrency security standard (CCSS) | B13: International | C13: Certification | E13: Crypto / blockchain | F13: Crypto platform security | G13: Startup / Mid-size | H13: Crypto trust | I13: ↓ breach risk 20–30% | J13: Third-party audit | K13: Security levels: Level 1 (Basic) → Level 2 (Standard) → Level 3 (Advanced — most intensive testing) [Each level independently certifiable; annual recertification required across all 10 security aspects] | L13: Certification level | M13: PDF certificate | N13: 2-6 months | O13: $10K - $200K | P13: ISO 27001 | Q13: Voluntary | R13: - Levels 1 , 2, 3 ; Achieving Level 3 (highest security) requires more intensive testing than Level 1. - Annual process (every 12 months) | S13: - Historical context: CCSS v1.0 released 2014; maintained by C4 (CryptoCurrency Certification Consortium) - Auditor's perspective: Key management practices (especially for cold storage) are the most scrutinised aspect - Links: cryptoconsortium.org/ccss | T13: Cryptocurrency exchanges, custodians, wallet providers, and DeFi platforms seeking institutional credibility. A priority before pursuing institutional partnerships or regulated market entry.
A14: NCSC Cyber Essentials | B14: UK | C14: Certification | E14: UK organisations | F14: Baseline cyber hygiene certification for UK organisations | G14: Startup / Small | H14: Baseline hygiene | I14: ↓ common attacks ~80% | J14: Self + assessor | K14: Certification tiers: Cyber Essentials (self-assessed, verified by assessor) → Cyber Essentials Plus (on-site technical testing) [CE Plus requires a passing CE first; both are independently certifiable] | L14: Certification | M14: PDF certificate | N14: 1-3 months | O14: $5k-$30k | P14: CIS18 | Q14: Mandatory (conditional) | R14: - 5 technical controls: firewalls, secure configuration, access control, malware protection, software patching - Cyber Essentials Plus adds vulnerability scanning and internal assessment - Required for UK government contracts involving personal data or certain technical services - Backed by NCSC (National Cyber Security Centre) | S14: - Historical context: Cyber Essentials launched 2014 by UK government; CE Plus added as enhanced tier shortly after - Auditor's perspective: Scope definition (what's in the assessed boundary) is the most common source of errors - Links: ncsc.gov.uk/cyberessentials | T14: UK-based organisations of any size — particularly those seeking UK government contracts or wanting the lowest-cost verifiable security baseline. Good first certification before progressing to ISO 27001.
A15: Risk & Control Self Assessment (RCSA ) | B15: International | C15: Assessment | E15: Financial services | F15: Internal risk & control evaluation | G15: Mid-size / Enterprise | H15: Risk prioritization | I15: ↓ loss events 15–30% | J15: Self | K15: Risk ratings: Critical / High / Medium / Low / Negligible [Not a maturity scale — ratings reflect inherent and residual risk levels per control; reassessed annually or after incidents] | L15: Risk assessment | M15: Internal report / GRC tool | N15: Ongoing | O15: Internal cost | P15: COSO | Q15: Voluntary | R15: Risk inventory, control effectiveness, residual risk | S15: - Historical context: RCSA emerged from Basel II operational risk framework requirements in the early 2000s - Auditor's perspective: Control effectiveness ratings (not just risk identification) are the most important and most frequently challenged aspect - Pairs with: ISO 31000, NIST CSF Identify function, COBIT risk management objectives | T15: Financial services firms subject to operational risk regulation (Basel, PRA, FCA). Should be in place before pursuing ISO 31000 or as an ongoing complement to a broader GRC programme.
A16: PCI SAQ | B16: International | C16: Assessment | E16: small merchants | F16: Payment card data security self assessment questionnare | G16: Startup / Mid-size | H16: Simplified compliance | I16: ↓ compliance cost 20–30% | J16: Self | K16: Self-assessment types: A / A-EP / B / B-IP / C / C-VT / D (complexity increases with cardholder data environment scope) [SAQ type determined by how card data is processed, not org maturity] | L16: Self-assessment | M16: PDF / portal submission | N16: 1-3 months | O16: $50K–$150K | P16: PCI DSS | Q16: Mandatory (conditional) | R16: Typically for level 2,3,4 merchants (lower txn volumes) and is an internal activity | S16: - Historical context: PCI DSS v1.0 launched 2004 by PCI SSC (Visa, Mastercard, Amex, Discover, JCB) - Auditor's perspective: Scope reduction is the highest-ROI activity — minimising CDE scope reduces both compliance cost and breach risk - Links: pcisecuritystandards.org | T16: Any merchant or service provider processing payment card transactions below Level 1 thresholds. Confirm SAQ type with acquiring bank before starting — wrong SAQ type is a common and costly mistake.
A17: PCI DSS | B17: International | C17: Audit | E17: Payment processors | F17: PCI audit performed by certified QSA | G17: Mid-size / Enterprise | H17: Payment security | I17: Avoid breach costs ($4M+ avg) | J17: Third-party audit | K17: Compliance status: Compliant / Non-Compliant [Annual QSA audit against 12 requirements and ~300 sub-requirements; findings graded: In Place / Not In Place / Not Applicable / Not Tested] | L17: ROC + AOC | M17: Formal audit report (PDF) | N17: 3-9 months | O17: $50K–$300K | P17: — | Q17: Mandatory (conditional) | R17: Typically required for level 1 merchants | S17: output: further breakdown with types of output include type of doc (tracking spreadsheet, eg), piece of paper you give customers, number of pages expected. | T17: Level 1 merchants processing 6M+ annual Visa transactions, or any merchant that has suffered a breach. Service providers processing 300K+ annual transactions are also typically in scope.
A18: FFIEC AAA | B18: US | C18: Regulation | E18: US banking / finance | F18: Banking authentication & access assurance | G18: Enterprise | H18: Strong auth controls | I18: ↓ fraud losses 20–40% | J18: Regulatory exam | K18: Maturity tiers: Baseline → Evolved → Advanced [Tiers reflect sophistication of authentication and access controls; assessed during regulatory examination] | L18: Exam findings | M18: Regulatory report | N18: 3-6 months | O18: $50k-$100k | P18: NIST 800-63 | Q18: Mandatory | R18: MFA, layered security, fraud detection, transaction monitoring. Typically for call center folks handling PII, applications dealing with PII etc | S18: - Historical context: FFIEC AAA guidance originally issued 2001; significantly updated 2005 and 2011 with online banking expansion - Auditor's perspective: Risk-based authentication — demonstrating layered controls beyond passwords — is the key examiner focus - Links: ffiec.gov/pdf/Auth-ITS-Final%2006-22-11%20(FFIEC%20Formated).pdf | T18: US banks, credit unions, mortgage servicers, and other FFIEC-supervised institutions. Should be aligned ahead of scheduled regulatory examinations — findings directly affect supervisory ratings.
A19: CIS18 | B19: International | C19: Framework | E19: All industries | F19: Prescriptive baseline controls | G19: Startup / Mid-size / Enterprise | H19: Practical controls | I19: ↓ cyber risk ~60–80% | J19: Self | K19: Implementation groups: IG1 (Basic — 56 safeguards, all orgs) → IG2 (Foundational — 74 additional) → IG3 (Organisational — 23 additional) [Groups are cumulative; IG1 is minimum baseline for all organisations regardless of size] | L19: Control score + roadmap | M19: Internal report | N19: 2-6 months | O19: $25k-$150k | P19: NIST CSF | Q19: Voluntary | R19: - 8 best-practice controls to strengthen defenses against common attacks - Phased implementation (IG1–IG3) based on organizational maturity, starting with cyber hygiene | S19: - Historical context: CIS Controls originally published as SANS Top 20 in 2008; transferred to CIS in 2015; v8 released 2021 - Auditor's perspective: IG1 completion alone significantly reduces breach likelihood and satisfies most cyber insurance requirements - Links: cisecurity.org/controls | T19: Organisations at the start of their security programme with limited budget. IG1 is achievable for any organisation and satisfies most cyber insurance minimum requirements. Start here before NIST CSF or ISO 27001.
A20: SOC 2 | B20: US / intl | C20: Certification | E20: SaaS, tech | F20: Trust services criteria audit covering security, availability, processing integrity, confidentiality, and privacy | G20: Startup / Mid-size / Enterprise | H20: Customer trust | I20: ↑ deal win rate 20–40% | J20: Third-party audit | K20: Engagement types: Type I (point-in-time design assessment) → Type II (operating effectiveness over 6–12 month period) [Not maturity levels — Type II is the standard most enterprise customers require] | L20: Audit report (Type I/II) | M20: Restricted PDF report | N20: 3–6 months (Type I) 6–12 months (Type II) | O20: $30K–$150K | P20: ISO 27001 | Q20: Voluntary | R20: - 5 Trust Service Criteria: Security, Availability, Processing Integrity, Confidentiality, Privacy - Not a certification — it's an attestation report - Type II most valued by enterprise customers - AICPA-governed | S20: - Auditor's perspective: SOC 2 Type II is the de facto enterprise trust signal in North America | T20: SaaS and cloud technology companies selling to US enterprise customers. SOC 2 Type II is the single highest-impact certification for removing North American enterprise procurement blockers.
A21: ISO 27001 | B21: International | C21: Certification | E21: SaaS, enterprises | F21: Establish, implement, maintain and continually improve an Information Security Management System (ISMS) | G21: Mid-size / Enterprise | H21: Global trust | I21: ↑ enterprise sales 20–30% | J21: Third-party audit | K21: Audit stages: Stage 1 (documentation and readiness review) → Stage 2 (on-site certification audit) → Surveillance audits (annual) → Recertification (every 3 years) [Pass/fail per stage — not a maturity scale] | L21: Certification + SoA | M21: PDF certificate + audit report | N21: 6–18 months | O21: $50K–$300K | P21: SOC 2 | Q21: Voluntary | R21: - 93 controls across 4 domains (ISO 27001:2022) / 114 controls (2013 version) - Pairs with ISO 27002 for implementation guidance - Globally recognised — often required for EU, UK, APAC contracts - Transition to 2022 version required | S21: - Historical context: Originally BS 7799, became ISO in 2005; major revision in 2013 and 2022 | T21: Technology companies, managed service providers, and any organisation selling to EU, UK, APAC, or Middle East enterprise customers. The international equivalent of SOC 2 — pursue both if operating globally.
A22: ISO 42001 | B22: International | C22: Certification | E22: AI-driven orgs | F22: Establish and maintain an AI Management System (AIMS) covering governance, risk, ethics, and transparency | G22: Mid-size / Enterprise | H22: AI governance | I22: ↓ AI/compliance risk 20–30% | J22: Third-party audit | K22: Audit stages: Stage 1 (documentation review) → Stage 2 (on-site audit) → Surveillance (annual) → Recertification (3-yearly) [Same audit cycle as ISO 27001; no numeric maturity tiers] | L22: Certification | M22: PDF certificate + audit report | N22: 6–12 months | O22: $50K–$200K | P22: NIST AI RMF | Q22: Voluntary | R22: - Published 2023 — world's first AI management system standard - Covers AI risk, transparency, human oversight, bias management - Strongly recommended alongside EU AI Act compliance - Pairs naturally with ISO 27001 | S22: - Quick useful links: iso.org/standard/81230.html - Auditor's perspective: early-mover advantage; limited certified auditors currently available | T22: Organisations already certified to ISO 27001 that are developing or deploying AI systems. Ideal for AI product companies seeking early regulatory credibility ahead of EU AI Act enforcement.
A23: HIPAA | B23: US | C23: Regulation | E23: Healthcare | F23: Protect the privacy and security of protected health information (PHI) through administrative, physical, and technical safeguards | G23: Startup / Mid-size / Enterprise | H23: Healthcare compliance | I23: Avoid fines up to $1.5M/year | J23: HHS OCR audit / internal self-assessment; business associate agreements (BAAs) required | K23: Compliance status: Compliant / Non-Compliant across 3 rules: Privacy Rule + Security Rule + Breach Notification Rule [No maturity tiers — compliance determined by presence and effectiveness of required safeguards] | L23: Compliance documentation | M23: Internal docs + policies | N23: 3–9 months (initial); ongoing | O23: $50K–$200K | P23: HITRUST | Q23: Mandatory | R23: - Applies to covered entities (providers, plans, clearinghouses) AND their business associates - Security Rule requires annual risk analysis - Breach Notification Rule: 60-day notification requirement - OCR fines range from $100 to $50,000 per violation | S23: - Historical context: Enacted 1996; HITECH Act 2009 expanded enforcement - Auditor's perspective: Risk analysis quality is the #1 audit finding area | T23: Healthcare providers, health plans, clearinghouses, and any business associate handling PHI. Non-negotiable for operating in the US healthcare market — should be the baseline before pursuing HITRUST.
... A47: CCPA / CPRA (California Consumer Privacy Act / Rights Act) | B47: US (California) | C47: Regulation | E47: US consumer-facing orgs | F47: Protect the privacy rights of California consumers — including the right to know, delete, opt-out of sale, and correct personal information — and establish the California Privacy Protection Agency (CPPA) as enforcement authority. | G47: Startup / Mid-size / Enterprise | H47: Consumer privacy | I47: Avoid fines + reputational loss | J47: Self / third-party audit | K47: Compliance status: Compliant / Non-Compliant [No maturity tiers — assessed against specific rights obligations and security requirements; CPRA added sensitive personal information category with enhanced protections] | L47: Privacy compliance | M47: Internal docs + public notice | N47: 3–6 months (initial); ongoing | O47: $30K–$200K | P47: GDPR | Q47: Mandatory | R47: - CCPA effective January 2020; CPRA amendments effective January 2023 - Thresholds: $25M+ annual gross revenue, OR 100,000+ consumers' personal information, OR 50%+ revenue from selling personal information - Key rights: know, delete, opt-out of sale/sharing, correct, limit use of sensitive PI, non-discrimination - CPRA created the CPPA — first dedicated US state privacy enforcement agency with independent budget - Other state laws modelled on CCPA: Virginia CDPA, Colorado CPA, Connecticut CTDPA — a joint programme satisfies most | S47: - Historical context: CCPA passed 2018 following Cambridge Analytica; CPRA passed via ballot initiative 2020 - Auditor's perspective: Data inventory and mapping quality is the foundation — organisations that cannot identify what personal data they hold cannot comply - Links: oag.ca.gov/privacy/ccpa / cppa.ca.gov | T47: Any for-profit business with California customers or employees that meets the revenue or data volume thresholds. Priority for US companies that have not yet assessed CPRA compliance, given the CPPA's increasingly active enforcement posture from 2024 onwards.

Sheet CompliancethatPays
A1: Compliance That Pays: ROI Guide by Org Stage - NOT FOR REVIEW YET
A2: See which certifications unlock revenue at each stage — with cost, timeline, and payback
A4: Use this guide to invest in compliance only when it drives pipeline. Skip what doesn’t pay back.
A5: Decision Matrix: Pick Your Path by Company Stage
A7: Org Stage | B7: Must Have First | C7: Add If… | D7: Skip Until… | E7: Total Investment* | F7: Time to Value | G7: Typical ROI Trigger
A8: Startup / Small <100 people | B8: NIST CSF 2.0 self-assess SOC 2 Type I | C8: ISO 27001 if you sell EU/global NIST AI RMF if AI is core product | D8: HITRUST, NIST RMF SOC 2 Type II unless enterprise deals require | E8: $50K–$200K | F8: 2–6 mo | G8: 1–2 deals >$100K unlock = 3x ROI Removes “are you audited?” blocker
A9: Mid-Size 100 - 2000 people | B9: SOC 2 Type II ISO 27001 | C9: HITRUST if >30% healthcare/PHI NIST AI RMF if AI is core | D9: NIST RMF unless >$10M fed pipeline | E9: $700K–$1.2M for both SOC 2 + ISO | F9: 12–16 mo | G9: Unlocks $1.2M+ in pipeline per year once SOC 2 + ISO are both complete 3x–5x ROI by Year 2
A10: Large Enterprise 2000+ | B10: ISO 27001 + SOC 2 NIST CSF 2.0 baseline | C10: ISO 42001 for AI governance HITRUST by BU NIST RMF/ATO for gov | D10: None – run unified control framework | E10: $1.05M–$1.85M total program | F10: 14–18 mo | G10: Security = revenue enabler Board risk visibility Avoid $4.45M avg breach cost

Sheet Exec-Cybe Risk&CompliancePortfo
A1: Framework/Assessment | B1: Geography | C1: Type | D1: Estimated Cost | E1: Best for (who should pursue) | F1: Typical Duration | G1: Business Value | H1: Quantified impact | I1: Assessment Mode (who manages) | J1: Levels | K1: Output Mode (word, pdf etc) | L1: Alternative | M1: Mandatory? | N1: Additional Info | O1: Additional details to consider /add to this sheet | P1: Who Should Prioritise First
A2: NIST CSF 2.0 | B2: US / International (adpt) | C2: Framework | D2: $50K–$200K | E2: All industries | F2: 2-6 months | G2: Business-aligned cybersecurity | H2: ↓ compliance effort 30–50% | I2: Self / Third-party | J2: Maturity tiers: Tier 1 (Partial) → Tier 2 (Risk Informed) → Tier 3 (Repeatable) → Tier 4 (Adaptive) [Not a pass/fail — tiers describe risk management practice maturity] | K2: Action plan | L2: ISO 27001, CIS18 | M2: Voluntary - Start here | N2: - covers 6 core functions - risk based prioritization emphasis - lower cost and customizable | O2: - Who should pursue | P2: Any organisation beginning a security programme or preparing for regulatory alignment. Ideal first framework for teams that need a common risk language before committing to a certification.
A3: HITRUST CSF | B3: US / International (adpt) | C3: Certification | D3: $150k-$500k | E3: Healthcare / fintech | F3: 6-12 months | G3: Unified cert reduces audit duplication | H3: ↓ audit effort 30–50% | I3: Third-party audit | J3: Certification levels: e1 (Essentials 1 — implemented) → i1 (Implemented 1 — self-assessed) → r2 (Risk-based 2 — validated by assessor) [Each level is independently certifiable] | K3: PDF certificate + formal assessment report | L3: ISO 27001, SOC 2 | M3: Voluntary | N3: - includes ~1,800 controls over 19 domains - time consuming, heavy costs and prescriptive | O3: - who manages / audits | P3: Healthcare-adjacent SaaS vendors, digital health platforms, and any business handling PHI that needs a single certification recognised by hospital systems, payers, and health-tech partners.
A4: NIST RMF | B4: US / International (adpt) | C4: Framework | D4: $200K–$800K | E4: Federal gov contractors | F4: 6–18 months | G4: Structured risk lifecycle | H4: ↓ control gaps 20–40% | I4: Self / Third-party | J4: Process stages: Categorise → Select → Implement → Assess → Authorise → Monitor [Stages lead to an ATO decision — not a maturity rating] | K4: PDF / formal government ATO package | L4: ISO 27001, 800-53 | M4: Mandatory (conditional) | N4: - Step-based process: Categorise → Select → Implement → Assess → Authorise → Monitor - Aligned with FISMA requirements for all US federal agencies - Produces a formal ATO (Authority to Operate) — the legal basis for operating a federal system - Common controls baseline drawn from NIST SP 800-53 | O4: - Business Value (why businesses /orgs should pursue a cert) - rationale | P4: Software and cloud vendors seeking or holding US federal contracts. Essential for any organisation within the DoD, civilian agency, or intelligence community supply chain.
A5: NIST AI RMF | B5: US / International (adpt) | C5: Framework | D5: $75k-$250k | E5: AL/ML adopters | F5: 3-9 months | G5: Trustworthy AI adoption | H5: ↓ AI risk exposure 20–30% | I5: Self | J5: Functional domains: Govern → Map → Measure → Manage [Profile-based — no numeric maturity score; progress measured via Current vs Target Profile gap] | K5: PDF profile document + action plan | L5: ISO 42001, EU AI Act | M5: Voluntary | N5: Govern–Map–Measure–Manage, bias, explainability, model risk | O5: - historical context of the framework/process/assessment | P5: Any organisation building, deploying, or procuring AI systems — particularly those selling into regulated industries or EU markets. A priority for AI product teams ahead of EU AI Act enforcement.
A6: NIST Privacy Framework | B6: US / International (adpt) | C6: Framework | D6: $50k-$200k | E6: All industries - Data driven orgs | F6: 2-6 months | G6: Privacy risk management | H6: ↓ privacy incidents 20–40% | I6: Self | J6: Maturity tiers: Tier 1 (Partial) → Tier 2 (Risk Informed) → Tier 3 (Repeatable) → Tier 4 (Adaptive) [Same tier structure as NIST CSF; privacy-specific profile added] | K6: PDF profile + gap analysis report | L6: ISO 27701, GDPR | M6: Voluntary | N6: - Voluntary framework — not a regulation - Pairs well with NIST CSF 2.0 and ISO 27701 - Covers 5 core functions: Identify-P, Govern-P, Control-P, Communicate-P, Protect-P - Maps to GDPR, CCPA, and APEC Privacy Framework | O6: - quick useful links/documentation (such as official guids , controls etc) - auditor's perspective of helpfulness (GRC perspective) | P6: Organisations subject to GDPR, CCPA, or handling consumer data at scale. Especially valuable for US companies needing a structured privacy risk programme without a mandatory regulatory driver.
A7: NIST SSDF-EO 14028 | B7: US / International (adpt) | C7: Framework | D7: $50K–$200K | E7: All Industries - Product/Eng orgs | F7: 3-6 months | G7: Secure SDLC | H7: ↓ vulnerabilities in prod 30–50% | I7: Self / Audit | J7: Task-level compliance: practices grouped into 4 groups (PO, RV, DT, RS) with task completion tracked [No numeric maturity tiers — compliance measured against task completion status] | K7: Formal attestation letter; SBOM documentation | L7: OWASP SAMM | M7: Mandatory (conditional) | N7: Secure coding, SBOM, DevSecOps | O7: - Historical context: SSDF published 2020; EO 14028 (May 2021) made it mandatory for federal software vendors - Auditor's perspective: SBOM quality and completeness are the primary assessment focus - Links: csrc.nist.gov/Projects/ssdf | P7: Software vendors supplying to US federal agencies or large enterprises that require SBOM documentation. Critical for any vendor whose software runs in government or critical infrastructure environments.
A8: Cyber Maturity Model Certification | B8: International | C8: Assessment | D8: $25k-$100k | E8: DoD contractors | F8: 2-4 months | G8: DoD market access | H8: Enables $M–$B defense contracts | I8: Third-party audit | J8: Maturity levels: Level 1 (Basic cyber hygiene) → Level 2 (Advanced — NIST 800-171) → Level 3 (Expert — NIST 800-172) [Each level is gate-controlled; Level 2+ requires C3PAO third-party assessment] | K8: PDF CMMC certificate | L8: NIST 800-171 | M8: Mandatory (conditional) | N8: - Level 1: 17 practices (FAR 52.204-21) — self-attestation - Level 2: 110 practices from NIST SP 800-171 — C3PAO required - Level 3: 24 additional practices from NIST SP 800-172 — government-led assessment - Mandatory for all DoD prime and subcontractors handling CUI | O8: - Historical context: CMMC 1.0 launched 2020; CMMC 2.0 (2021) streamlined from 5 levels to 3 - Auditor's perspective: Gap assessment against NIST SP 800-171 is essential before engaging a C3PAO - Links: dodcmmc.mil | P8: US defence contractors and subcontractors at any tier of the DoD supply chain. Required for contract award — organisations should confirm their CMMC level requirement before beginning.
A9: NIS2 Directive | B9: EU | C9: Regulation | D9: $100K–$400K | E9: EU critical infra | F9: 6–12 months | G9: EU compliance | H9: Avoid fines up to 2% revenue | I9: Regulatory audit | J9: Compliance status: Compliant / Partially Compliant / Non-Compliant [Regulation — no maturity tiers; compliance measured against 10 minimum security measures] | K9: PDF compliance report; regulatory submission | L9: ISO 27001 | M9: Mandatory | N9: Risk mgmt, incident reporting, governance | O9: - Historical context: NIS2 replaced NIS1 Directive (2016); member states had until October 2024 to transpose - Auditor's perspective: Supply chain security (Article 21) is the area organisations most commonly underestimate - Links: eur-lex.europa.eu/NIS2 | P9: EU-based operators of essential services (energy, transport, health, water, digital infrastructure) and important entities. Also relevant for non-EU companies with significant EU operations.
A10: EU AI Act | B10: EU | C10: Regulation | D10: $150k-$500k | E10: AI companies in EU | F10: 6-18 months | G10: AI compliance | H10: Avoid fines up to 6% revenue | I10: Regulatory audit | J10: Risk-based tiers: Prohibited / High-risk / Limited-risk / Minimal-risk [Tier determined by AI system use case, not org maturity; High-risk systems require conformity assessment] | K10: PDF compliance declaration; CE marking documentation | L10: ISO 42001 | M10: Mandatory | N10: World’s first legally binding AI framework, regulating systems by risk to ensure safety, transparency, ethics, and protection of fundamental rights. | O10: NIST SP | P10: Organisations developing or deploying AI systems in the EU, or selling AI-enabled products to EU customers. Priority for any company with high-risk AI use cases (HR, credit, healthcare, law enforcement).
A11: DORA | B11: EU | C11: Regulation | D11: $25M - $170M | E11: EU financial services | F11: 6-12+ months | G11: Operational resilience | H11: ↓ downtime losses 20–40% | I11: Regulatory audit | J11: Compliance status: Compliant / Non-Compliant [Regulation — no maturity tiers; assessed across 5 ICT risk pillars: Governance, Protection, Detection, Response, Recovery] | K11: PDF compliance report; regulatory submission | L11: ISO 22301 | M11: Mandatory | N11: to ensure financial entities can withstand, respond to, and recover from ICT (Information and Communication Technology) disruptions and cyberattacks. | O11: - Historical context: DORA finalised November 2022; application date January 17, 2025 - Auditor's perspective: ICT third-party register and contractual requirements (Article 30) are the most operationally complex aspect - Links: eur-lex.europa.eu/DORA | P11: EU-regulated financial entities: banks, investment firms, insurers, payment institutions, crypto-asset service providers. Also relevant for their critical ICT third-party providers.
A12: Cryptocurrency security standard (CCSS) | B12: International | C12: Certification | D12: $10K - $200K | E12: Crypto / blockchain | F12: 2-6 months | G12: Crypto trust | H12: ↓ breach risk 20–30% | I12: Third-party audit | J12: Security levels: Level 1 (Basic) → Level 2 (Standard) → Level 3 (Advanced — most intensive testing) [Each level independently certifiable; annual recertification required across all 10 security aspects] | K12: PDF level certificate | L12: ISO 27001 | M12: Voluntary | N12: - Levels 1 , 2, 3 ; Achieving Level 3 (highest security) requires more intensive testing than Level 1. - Annual process (every 12 months) | O12: - Historical context: CCSS v1.0 released 2014; maintained by C4 (CryptoCurrency Certification Consortium) - Auditor's perspective: Key management practices (especially for cold storage) are the most scrutinised aspect - Links: cryptoconsortium.org/ccss | P12: Cryptocurrency exchanges, custodians, wallet providers, and DeFi platforms seeking institutional credibility. A priority before pursuing institutional partnerships or regulated market entry.
... A46: CCPA / CPRA (California Consumer Privacy Act / Rights Act) | B46: US | C46: Regulation | D46: $30K–$200K | E46: US consumer-facing orgs | F46: 3–6 months (initial); ongoing | G46: Consumer privacy | H46: Avoid fines + reputational loss | I46: Self / third-party audit | J46: Compliance status: Compliant / Non-Compliant [No maturity tiers — assessed against specific rights obligations and security requirements; CPRA added sensitive personal information category with enhanced protections] | K46: Internal documentation; public-facing privacy notice; data subject request logs | L46: GDPR | M46: Mandatory | N46: - CCPA effective January 2020; CPRA amendments effective January 2023 - Thresholds: $25M+ annual gross revenue, OR 100,000+ consumers' personal information, OR 50%+ revenue from selling personal information - Key rights: know, delete, opt-out of sale/sharing, correct, limit use of sensitive PI, non-discrimination - CPRA created the CPPA — first dedicated US state privacy enforcement agency with independent budget - Other state laws modelled on CCPA: Virginia CDPA, Colorado CPA, Connecticut CTDPA — a joint programme satisfies most | O46: - Historical context: CCPA passed 2018 following Cambridge Analytica; CPRA passed via ballot initiative 2020 - Auditor's perspective: Data inventory and mapping quality is the foundation — organisations that cannot identify what personal data they hold cannot comply - Links: oag.ca.gov/privacy/ccpa / cppa.ca.gov | P46: Any for-profit business with California customers or employees that meets the revenue or data volume thresholds. Priority for US companies that have not yet assessed CPRA compliance, given the CPPA's increasingly active enforcement posture from 2024 onwards.
A47: PIPEDA | B47: Canada

Sheet FMACerts Insights - do not use
A1: Executive Cybersecurity Maturity Dashboard - 1CISO
A3: Sheet 3 of 3 | Auto-populated from Maturity Tracker | For executive and board reporting
A5: Frameworks Tracked | B5: Avg Current Maturity | C5: Avg Target Maturity | D5: Avg Gap | E5: At Target (Score ≥4) | F5: Critical (Score <2)
A6: =COUNTA('Exec-Cybe Risk&CompliancePortfo'!A2:A58) -> 46 | B6: N/A | C6: N/A | D6: N/A | E6: 0 | F6: 0
A8: Framework Type Breakdown
A9: Framework | B9: Certification | C9: Regulation | D9: Self-Assessment | E9: Audit | F9: Assessment
A10: =COUNTIF('Exec-Cybe Risk&CompliancePortfo'!$C$2:$C$59,"Framework") -> 11 | B10: =COUNTIF('Exec-Cybe Risk&CompliancePortfo'!$C$2:$C$59,B9) -> 13 | C10: =COUNTIF('Exec-Cybe Risk&CompliancePortfo'!$C$2:$C$59,C9) -> 11 | D10: =COUNTIF('Exec-Cybe Risk&CompliancePortfo'!$C$2:$C$59,D9) -> 0 | E10: =COUNTIF('Exec-Cybe Risk&CompliancePortfo'!$C$2:$C$59,E9) -> 2 | F10: =COUNTIF('Exec-Cybe Risk&CompliancePortfo'!$C$2:$C$59,F9) -> 8
A12: Framework-by-Framework Maturity Summary
A13: Framework | B13: Type | C13: Current Maturity | D13: Target Maturity | E13: Gap | F13: Q4 Progress | G13: Status | H13: Owner | I13: Next Review | J13: Priority Focus
A14: ='Exec-Cybe Risk&CompliancePortfo'!A2 -> NIST CSF 2.0 | B14: ='Exec-Cybe Risk&CompliancePortfo'!C2 -> Framework | C14: 0 | D14: 0 | F14: 0 | G14: 0 | H14: 0 | I14: 0 | J14: 0
A15: ='Exec-Cybe Risk&CompliancePortfo'!A3 -> HITRUST CSF | B15: Certification | C15: 0 | D15: 0 | F15: 0 | G15: 0 | H15: 0 | I15: 0 | J15: 0
A16: ='Exec-Cybe Risk&CompliancePortfo'!A4 -> NIST RMF | B16: Framework | C16: 0 | D16: 0 | F16: 0 | G16: 0 | H16: 0 | I16: 0 | J16: 0
A17: ='Exec-Cybe Risk&CompliancePortfo'!A5 -> NIST AI RMF | B17: Framework | C17: 0 | D17: 0 | F17: 0 | G17: 0 | H17: 0 | I17: 0 | J17: 0
A18: ='Exec-Cybe Risk&CompliancePortfo'!A6 -> NIST Privacy Framework | B18: Framework | C18: 0 | D18: 0 | F18: 0 | G18: 0 | H18: 0 | I18: 0 | J18: 0
A19: ='Exec-Cybe Risk&CompliancePortfo'!A7 -> NIST SSDF-EO 14028 | B19: Framework | C19: 0 | D19: 0 | F19: 0 | G19: 0 | H19: 0 | I19: 0 | J19: 0
A20: ='Exec-Cybe Risk&CompliancePortfo'!A8 -> Cyber Maturity Model Certification | B20: Assessment | C20: 0 | D20: 0 | F20: 0 | G20: 0 | H20: 0 | I20: 0 | J20: 0
A21: ='Exec-Cybe Risk&CompliancePortfo'!A9 -> NIS2 Directive | B21: Regulation | C21: 0 | D21: 0 | F21: 0 | G21: 0 | H21: 0 | I21: 0 | J21: 0
A22: ='Exec-Cybe Risk&CompliancePortfo'!A10 -> EU AI Act | B22: Regulation | C22: 0 | D22: 0 | F22: 0 | G22: 0 | H22: 0 | I22: 0 | J22: 0
A23: ='Exec-Cybe Risk&CompliancePortfo'!A11 -> DORA | B23: Regulation | C23: 0 | D23: 0 | F23: 0 | G23: 0 | H23: 0 | I23: 0 | J23: 0
A24: ='Exec-Cybe Risk&CompliancePortfo'!A12 -> Cryptocurrency security standard (CCSS) | B24: Certification | C24: 0 | D24: 0 | F24: 0 | G24: 0 | H24: 0 | I24: 0 | J24: 0
A25: ='Exec-Cybe Risk&CompliancePortfo'!A13 -> NCSC Cyber Essentials | B25: Audit | C25: 0 | D25: 0 | F25: 0 | G25: 0 | H25: 0 | I25: 0 | J25: 0
A26: ='Exec-Cybe Risk&CompliancePortfo'!A14 -> Risk & Control Self Assessment (RCSA ) | B26: Certification | C26: 0 | D26: 0 | F26: 0 | G26: 0 | H26: 0 | I26: 0 | J26: 0
... A38: ='Exec-Cybe Risk&CompliancePortfo'!A26 -> StateRAMP/ GovRAMP | B38: Framework | C38: 0 | D38: 0 | F38: 0 | G38: 0 | H38: 0 | I38: 0 | J38: 0
A39: ='Exec-Cybe Risk&CompliancePortfo'!A27 -> COBIT
A40: ='Exec-Cybe Risk&CompliancePortfo'!A28 -> COSO
A41: ='Exec-Cybe Risk&CompliancePortfo'!A29 -> GLBA
A42: ='Exec-Cybe Risk&CompliancePortfo'!A30 -> CSA STAR
A43: ='Exec-Cybe Risk&CompliancePortfo'!A31 -> GDPR (General Data Protection Regulation)
A44: ='Exec-Cybe Risk&CompliancePortfo'!A32 -> ISO 27701
A45: ='Exec-Cybe Risk&CompliancePortfo'!A33 -> SOC 1 (SSAE 18)
A46: ='Exec-Cybe Risk&CompliancePortfo'!A34 -> ISO 22301
A47: ='Exec-Cybe Risk&CompliancePortfo'!A35 -> SWIFT CSP (Customer Security Programme)
A48: ='Exec-Cybe Risk&CompliancePortfo'!A36 -> TISAX (Trusted Information Security Assessment Exchange)
A49: ='Exec-Cybe Risk&CompliancePortfo'!A37 -> NERC CIP (Critical Infrastructure Protection)
A50: ='Exec-Cybe Risk&CompliancePortfo'!A38 -> IEC 62443
... A52: ='Exec-Cybe Risk&CompliancePortfo'!A40 -> C2M2 (Cybersecurity Capability Maturity Model)

Sheet Certifications
A1: Certification Name | B1: Authoritative Body | C1: First Source (Multimedia -Audio/Video) | D1: First Source (Text) | E1: Secondary/third-party trusted sources | F1: Comments/Questions for Lisa
A2: SOC 2 | B2: AICPA | D2: aicpa-cima.com/soc | E2: https://goteleport.com/blog/ai-agents-soc-2/ | F2: will have to review the folder Lisa shared ( awaiting folder access)
A3: ISO 27001 | B3: ISO / IEC | D3: iso.org/standard/27001 | F3: will have to review the folder Lisa shared ( awaiting folder access)
A4: ISO 42001 | B4: ISO / IEC | D4: iso.org/standard/42001 | F4: will have to review the folder Lisa shared ( awaiting folder access)
A5: HIPAA | B5: HHS | D5: hhs.gov/hipaa | F5: will have to review the folder Lisa shared ( awaiting folder access)
A6: SOX | B6: SEC | D6: sec.gov/sox | E6: sox-compliance-keysteps
E7: sox-investor-auditor-regulator-perspective
A8: NYDFS
A9: FedRAMP | B9: US Federal Government | C9: fedramp-overview | D9: fedramp.gov | E9: knox-fedramp-ato90days
D10: fedramp/git | E10: fedramp-ato-automation
E11: navigate-fedramp-landscape
E12: fedramp-from-inception-thru-ato
A13: StateRAMP/ GovRAMP | B13: State Government | C13: stateramp-Intro | D13: stateramp-journey | E13: what-is-stateramp
C14: 2025-govramp-summit | D14: govramp-requirements | E14: everything-you-need-to-know-stateramp
C15: govramp-annual-edu-event
C16: govramp-faq
C17: govramp-template-documents

Sheet Security Program
A1: For internal review with Lisa
H3: Timeline View of Security Program Delivery This timeline provides a directional view of the security program rollout. While timelines are not set in stone and may evolve based on business priorities, the expectation is to deliver the following key artifacts by the time we reach Phase (6): 1) a. Security Compliance Program Strategy: A comprehensive strategy tailored to multiple audiences, including executive leadership, board members, and operational/non-board stakeholders. 1.b Strategy we can share with prospects/customers 2) Policy Management Framework: 2a. Development of policies, standards, and procedures (PSP) for internal 1CISO 2b. reusable templates to support customer needs and external engagements. Note - these PSP's will be designed inline with the ISO standards
A6: Original copy here --> https://lucid.app/lucidspark/180bd713-d386-487c-9c42-97328ab84e23/edit?invitationId=inv_012c1c1f-b9b8-43d7-9f95-15ae1877ce66
H8: WHAT | I8: High level program overview
I9: This is a single slide view
H11: Audience | I11: Executive / board
I13: 1) Do you think we should add cost and ROI here ?? this is available in Version 2 -slide 2 below 2) What are your thoughts in expanding this further and have another slide that would contain additional info as shown in version 2 - slide 2 below ?
I14: 3) Is this too simple ? do you think its better to remove 2 horizontal small bars (unified control framework , AIMS)?
H19: 1) Audit firms -recommendation to select /not select audit firms for SOC2 audits or certifications
H20: Note from latha - Parking this for now I will get back to you later
H31: WHAT | I31: High level program overview
I32: This has slightly more detail
H34: Audience | I34: Executive / board
I36: 1) Is it too much info ? 2) do you think we can get to somewhere between version 1 and 2 ? 3) let me know your thoughts on slide 2 of this version 2 Note - The numbers require further discussion and are not yet finalized.
I37: 3) Is this too simple ? do you think its better to remove 2 horizontal small bars (unified control framework , AIMS)?
A59: Option 3
A64: More detailed view yet to come

Sheet Secompsummary-Temptobedeleted
A1: Security Compliance Program — Executive Summary
B2: Phase 1 · Mo 1–2 | C2: Phase 2 · Mo 3–4 | D2: Phase 3 · Mo 5–10 | E2: Phase 4 · Mo 10–14 | F2: Phase 5 · Mo 14–18+
B3: Governance & Strategy | C3: Risk & Control Framework | D3: Control Execution | E3: Assurance & Audit | F3: Metrics & Improvement
A4: What to expect | B4: Clear ownership & accountability - Defined scope (ISMS + AIMS) - Org-wide security culture | C4: Standardised risk assessment Unified control framework Documented policies & SoA | D4: Security controls operational Security embedded in Eng (DevSecOps) Managed 3rd-party & AI risks | E4: Verified control effectiveness Audit readiness (ISO, SOC2) Continuous monitoring & early detection | F4: Measurable security posture Executive insights into risk & control health Continuous program maturity
A5: Business value | B5: Reduces regulatory risk Enables faster decisions Builds board/customer trust | C5: Accelerates audits & certs Improves consistency Enables scalable compliance | D5: CIA protection Secure product releases Lowers vendor & AI risk | E5: Builds external trust Reduces audit fatigue Cert readiness demonstrated | F5: Aligns security to biz goals Demonstrates ROI Program maturity optimised
A6: Who owns it | B6: Sponsor: CEO / Board Owns: CISO (Program Owner) GRC · 2LoD | C6: Owns: CISO GRC Leads · 2LoD | D6: Owns: Tech & Biz Owners GRC 2LoD · Engineering 1LoD: ISO Support iLoD | E6: Owns: CISO + GRC Internal Audit 3LoD (independent) | F6: Owns: CISO GRC · Board reporting cadence
A7: Certifications | B7: Foundation only | C7: Framework design | D7: ISO 27001 obs. begins SOC 2 obs. Mo 8–14 | E7: ISO 27001 — Mo 14 SOC 2 Type II — Mo 16 ISO 42001 — Mo 18 | F7: Annual recertification & surveillance audits
A8: What does it cost | B8: $80–150K CISO, GRC tooling, charter | C8: $120–270K Gap analysis, policies, framework | D8: $400–700K Tooling, DevSecOps, IR retainer | E8: $300–500K Audit fees, pen testing, cert costs | F8: $150–250K Ongoing monitoring, annual audits
A9: ROI & value realised | B9: Investment phase Groundwork for all downstream returns | C9: Investment phase Policies reduce regulatory exposure from Mo 4 | D9: ~$500K+ value begins Faster enterprise sales cycles Reduced breach likelihood (controls live) DevSecOps reduces rework cost Vendor risk incidents avoided | E9: ~$1.2M+ cumulative value ISO 27001 unlocks new enterprise contracts SOC 2 removes procurement blocker Audit fatigue eliminated Breach cost avoidance ($4.45M avg) | F9: 3× – 5× ROI by Year 2 ISO 42001 competitive differentiator Security = revenue enabler Regulatory fine avoidance Board-level risk visibility
A10: Total Program Investment - 18 Months Lean (build-heavy) to acceleerated (consultant-heavy) model - excludes internal headcount opportunity cost | D10: $1.05M - $1.85M Delivers ISO 27001 SOC2 Type II + ISO 42001 Certifications (geography-specific certifications that need to be considered on a need basis)
